{"cameraMode":{"drawMode":0,"name":"Shaded","section":"Shading Mode"},"sceneLighting":true,"audioPlay":false,"sceneViewState":{"m_AlwaysRefresh":false,"showFog":true,"showSkybox":true,"showFlares":true,"showImageEffects":true,"showParticleSystems":true,"showVisualEffectGraphs":true,"m_FxEnabled":true},"in2DMode":false,"pivot":{"x":408.49371337890627,"y":85.45249938964844,"z":0.0},"rotation":{"x":-0.21576173603534699,"y":0.10694985091686249,"z":-0.023784425109624864,"w":-0.9702838659286499},"size":457.585693359375,"orthographic":false}